.gitignore
.pylintrc
.readthedocs.yml
.travis.yml
CODE_OF_CONDUCT.md
LICENSE
README.rst
adafruit_lsm303agr_mag.py
requirements.txt
setup.py
adafruit_circuitpython_lsm303agr_mag.egg-info/PKG-INFO
adafruit_circuitpython_lsm303agr_mag.egg-info/SOURCES.txt
adafruit_circuitpython_lsm303agr_mag.egg-info/dependency_links.txt
adafruit_circuitpython_lsm303agr_mag.egg-info/requires.txt
adafruit_circuitpython_lsm303agr_mag.egg-info/top_level.txt
docs/api.rst
docs/conf.py
docs/examples.rst
docs/index.rst
docs/_static/favicon.ico
examples/lsm303agr_mag_interrupt.py
examples/lsm303agr_mag_simpletest.py