Metadata-Version: 2.1
Name: adafruit-circuitpython-lsm303agr-mag
Version: 1.0.0
Summary: CircuitPython library for LSM303AGR's 3-axis magnetometer.
Home-page: https://github.com/adafruit/Adafruit_CircuitPython_LSM303AGR_Mag
Author: Adafruit Industries
Author-email: circuitpython@adafruit.com
License: MIT
Keywords: adafruit lsm303 6dof 6-dof magnetometer axisbreakout hardware micropython circuitpython
Platform: UNKNOWN
Classifier: Development Status :: 3 - Alpha
Classifier: Intended Audience :: Developers
Classifier: Topic :: Software Development :: Libraries
Classifier: Topic :: System :: Hardware
Classifier: License :: OSI Approved :: MIT License
Classifier: Programming Language :: Python :: 3
Classifier: Programming Language :: Python :: 3.4
Classifier: Programming Language :: Python :: 3.5
